{"cameraMode":{"drawMode":0,"name":"Shaded","section":"Shading Mode"},"sceneLighting":false,"audioPlay":false,"sceneViewState":{"m_AlwaysRefresh":false,"showFog":true,"showSkybox":false,"showFlares":true,"showImageEffects":true,"showParticleSystems":true,"showVisualEffectGraphs":true,"m_FxEnabled":true},"in2DMode":false,"pivot":{"x":23.9831485748291,"y":1.7060377597808838,"z":18.829439163208009},"rotation":{"x":0.02962152659893036,"y":-0.9045444130897522,"z":0.4209910035133362,"w":0.06362080574035645},"size":2.899690628051758,"orthographic":false}